gorpyter/__init__.py
gorpyter-0.6.6.dist-info/METADATA
gorpyter-0.6.6.dist-info/WHEEL
gorpyter-0.6.6.dist-info/top_level.txt
gorpyter-0.6.6.dist-info/RECORD
