Metadata-Version: 2.1
Name: gorpyter
Version: 0.6.6
Summary: Python wrapper for GOR's R SDK with Pandas serialization.
Home-page: https://pypi.org/project/gorpyter/
Author: Layne Sadler
Author-email: layne.sadler@gmail.com
License: WXNC
Platform: UNKNOWN
Classifier: Programming Language :: Python :: 3
Classifier: License :: OSI Approved :: MIT License
Classifier: Operating System :: OS Independent
Requires-Dist: rpy2 (>=3.0.5)
Requires-Dist: tzlocal (>=2.0.0)
Requires-Dist: pandas (>=0.25.0)
Requires-Dist: numpy (>=1.17.0)
